<?xml version="1.0" encoding="utf-8" ?>
<dwsync>
<file name="8020select.png" server="ftp.baldingremedies.org" local="130037523600000000" remote="130037523600000000" />
<file name="adoptahydrant.png" server="ftp.baldingremedies.org" local="130037523600000000" remote="130037523600000000" />
<file name="breakingnews.png" server="ftp.baldingremedies.org" local="130037523600000000" remote="130037523600000000" />
<file name="fleetio.png" server="ftp.baldingremedies.org" local="130037523600000000" remote="130037523600000000" />
<file name="gathercontent.png" server="ftp.baldingremedies.org" local="130037523600000000" remote="130037523600000000" />
<file name="jshint.png" server="ftp.baldingremedies.org" local="130037523600000000" remote="130037523600000000" />
<file name="kippt.png" server="ftp.baldingremedies.org" local="130037523600000000" remote="130037523600000000" />
<file name="soundready.png" server="ftp.baldingremedies.org" local="130037523600000000" remote="130037523600000000" />
<file name="8020select.png" server="ftp.becauseofus.net" local="130037523600000000" remote="130037746800000000" />
<file name="adoptahydrant.png" server="ftp.becauseofus.net" local="130037523600000000" remote="130037746800000000" />
<file name="breakingnews.png" server="ftp.becauseofus.net" local="130037523600000000" remote="130037746800000000" />
<file name="fleetio.png" server="ftp.becauseofus.net" local="130037523600000000" remote="130037746800000000" />
<file name="gathercontent.png" server="ftp.becauseofus.net" local="130037523600000000" remote="130037746800000000" />
<file name="jshint.png" server="ftp.becauseofus.net" local="130037523600000000" remote="130037746800000000" />
<file name="kippt.png" server="ftp.becauseofus.net" local="130037523600000000" remote="130037746800000000" />
<file name="soundready.png" server="ftp.becauseofus.net" local="130037523600000000" remote="130037746800000000" />
</dwsync>